{
  "nombreNegocio": "Acabados Profesionales Lima",
  "slogan": "Expertos en Pintura, Drywall y Acabados de Calidad",
  "descripcion": "18 años transformando espacios con calidad y confianza",
  "contacto": {
    "telefono": "966 917 638",
    "email": "",
    "whatsapp": "51966917638",
    "horario": "Lunes a Sábado: 8:00 AM - 6:00 PM"
  },
  "redes": {
    "facebook": "https://facebook.com/acabadoslima",
    "instagram": "https://instagram.com/acabadoslima"
  },
  "estadisticas": {
    "añosExperiencia": 18,
    "proyectosCompletados": 150,
    "clientesSatisfechos": 120
  },
  "seo": {
    "titulo": "Servicios de Construcción y Acabados | Acabados Profesionales",
    "descripcion": "Expertos en pintura, drywall y acabados de calidad. Garantía de calidad y años de experiencia.",
    "keywords": "acabados lima, pintura lima, enchapado, drywall, construcción"
  }
}